mangodm/__init__.py
mangodm/main.py
mangodm-0.1.5.dist-info/LICENSE
mangodm-0.1.5.dist-info/METADATA
mangodm-0.1.5.dist-info/WHEEL
mangodm-0.1.5.dist-info/top_level.txt
mangodm-0.1.5.dist-info/RECORD
