Metadata-Version: 2.1
Name: mangodm
Version: 0.1.5
Summary: mangODM - simple async ODM for mongodb.
Home-page: https://github.com/Exillite/mangodm
Author: Alexander Rodionov
Author-email: sa27shal@gmail.com
Classifier: Programming Language :: Python :: 3
Classifier: License :: OSI Approved :: MIT License
Requires-Python: >=3.7
License-File: LICENSE
